LICENSE
README.md
setup.py
test/test_log.py
test/test_time.py
torch4keras/__init__.py
torch4keras/callbacks.py
torch4keras/cli.py
torch4keras/model.py
torch4keras.egg-info/PKG-INFO
torch4keras.egg-info/SOURCES.txt
torch4keras.egg-info/dependency_links.txt
torch4keras.egg-info/entry_points.txt
torch4keras.egg-info/requires.txt
torch4keras.egg-info/top_level.txt
torch4keras/snippets/__init__.py
torch4keras/snippets/data_process.py
torch4keras/snippets/import_utils.py
torch4keras/snippets/log.py
torch4keras/snippets/misc.py
torch4keras/snippets/monitor.py
torch4keras/snippets/shell.py
torch4keras/trainer/__init__.py
torch4keras/trainer/accelerate.py
torch4keras/trainer/base.py
torch4keras/trainer/ddp.py
torch4keras/trainer/deepspeed.py
torch4keras/trainer/dp.py
torch4keras/trainer/utils.py