Metadata-Version: 2.1
Name: torch4keras
Version: 0.3.2
Summary: Use torch like keras
Home-page: https://github.com/Tongjilibo/torch4keras
Author: Tongjilibo
License: Apache License
License-File: LICENSE
Requires-Dist: numpy
Requires-Dist: packaging
